gaarf_core/__init__.py
gaarf_core/api_clients.py
gaarf_core/base_query.py
gaarf_core/exceptions.py
gaarf_core/parsers.py
gaarf_core/query_editor.py
gaarf_core/report.py
gaarf_core/report_fetcher.py
gaarf_core-0.0.2.dist-info/METADATA
gaarf_core-0.0.2.dist-info/WHEEL
gaarf_core-0.0.2.dist-info/top_level.txt
gaarf_core-0.0.2.dist-info/RECORD
